wisio/__init__.py
wisio/analyzer.py
wisio/scoring.py
wisio/config.py
wisio/analysis.py
wisio/rules.py
wisio/constants.py
wisio/dftracer.py
wisio/output.py
wisio/recorder.py
wisio/rule_engine.py
wisio/analysis_utils.py
wisio/types.py
wisio/darshan.py
wisio/__main__.py
wisio/utils/__init__.py
wisio/utils/logger.py
wisio/utils/dask_agg.py
wisio/utils/yaml_utils.py
wisio/utils/file_utils.py
wisio/utils/common_utils.py
wisio/utils/collection_utils.py
wisio/utils/distributed_plugins.py
wisio/utils/json_encoders.py
wisio/utils/dask_utils.py
wisio.libs/libbrotlienc-6e59301f.so.1.1.0
wisio.libs/libabsl_strings-7c14e122.so.20220623.0.0
wisio.libs/libprotobuf-c9dae436.so.32.0.12
wisio.libs/libxml2-18f02231.so.2.9.14
wisio.libs/libkrb5-52c143c9.so.3.3
wisio.libs/libabsl_str_format_internal-9731d476.so.20220623.0.0
wisio.libs/liblber-6f6935b2.so.2.0.200
wisio.libs/libopen-rte-26467e1d.so.40.30.3
wisio.libs/libgnutls-a64da3b2.so.30.37.1
wisio.libs/libabsl_time-32701d0d.so.20220623.0.0
wisio.libs/libabsl_raw_logging_internal-ba514da0.so.20220623.0.0
wisio.libs/libcom_err-022943b3.so.2.1
wisio.libs/librtmp-15a2a75e.so.1
wisio.libs/libabsl_throw_delegate-336db430.so.20220623.0.0
wisio.libs/libhogweed-c3c60613.so.6.8
wisio.libs/libthrift-0-696d2dec.19.0.so
wisio.libs/libmpi_cxx-bf970d3b.so.40.30.1
wisio.libs/libabsl_base-3e8f0569.so.20220623.0.0
wisio.libs/libssl-e50e007b.so.3
wisio.libs/libsnappy-955acc8e.so.1.1.10
wisio.libs/libkeyutils-f4821441.so.1.10
wisio.libs/liblzma-a9793942.so.5.4.5
wisio.libs/libp11-kit-c6b469a0.so.0.3.1
wisio.libs/libgmp-0ccdfb6d.so.10.5.0
wisio.libs/libbrotlicommon-a91ead09.so.1.1.0
wisio.libs/libpsl-ae6c5a9a.so.5.3.4
wisio.libs/libtasn1-7c9c7830.so.6.6.3
wisio.libs/libnghttp2-398c6d20.so.14.26.0
wisio.libs/libparquet-60f4e07d.so.2100.0.0
wisio.libs/libkrb5support-8e1ef5a4.so.0.1
wisio.libs/libabsl_bad_optional_access-5e287863.so.20220623.0.0
wisio.libs/libffi-00f593fe.so.8.1.4
wisio-0.1.1.dist-info/entry_points.txt
wisio-0.1.1.dist-info/METADATA
wisio-0.1.1.dist-info/RECORD
wisio-0.1.1.dist-info/WHEEL
