Metadata-Version: 2.1
Name: wisio
Version: 0.1.1
Summary: Analyze, visualize, and understand I/O performance issues in HPC workflows
Author-Email: Izzet Yildirim <izzetcyildirim@gmail.com>
Maintainer-Email: Izzet Yildirim <izzetcyildirim@gmail.com>
Classifier: Development Status :: 3 - Alpha
Classifier: Intended Audience :: Science/Research
Classifier: License :: OSI Approved :: MIT License
Classifier: Programming Language :: Python
Classifier: Programming Language :: Python :: 3
Classifier: Programming Language :: Python :: 3.8
Classifier: Programming Language :: Python :: 3.9
Classifier: Programming Language :: Python :: 3.10
Classifier: Programming Language :: Python :: 3 :: Only
Classifier: Topic :: Scientific/Engineering
Classifier: Topic :: Software Development :: Build Tools
Classifier: Typing :: Typed
Project-URL: documentation, https://grc.iit.edu/docs/category/wisio/
Project-URL: source, https://github.com/grc-iit/wisio
Project-URL: tracker, https://github.com/grc-iit/wisio/issues
Requires-Python: <3.11,>=3.8
Requires-Dist: dask[bag,dataframe,distributed]~=2023.4.0
Requires-Dist: dask_jobqueue~=0.8.0
Requires-Dist: hydra-core~=1.3.0
Requires-Dist: inflect==7.0
Requires-Dist: jinja2>=3.0
Requires-Dist: numpy==1.24.3
Requires-Dist: matplotlib>=3.6.0
Requires-Dist: pandas>=2.0
Requires-Dist: portion>=2.4.0
Requires-Dist: pyarrow>=13
Requires-Dist: pyyaml>=5.4
Requires-Dist: rich==13.6.0
Requires-Dist: scikit-learn~=1.3.0
Requires-Dist: scipy~=1.10.0
Requires-Dist: venn==0.1.3
Provides-Extra: darshan
Requires-Dist: darshan>=3.4; extra == "darshan"
Provides-Extra: dftracer
Requires-Dist: zindex_py==0.0.5; extra == "dftracer"
